[{"name": "EQ to Truthear x Crinacle Red (AVG)", "preamp": 0.0, "parametric": true, "bands": [{"type": 0, "channels": 0, "frequency": 90, "q": 0, "gain": 0.0, "color": 0}, {"type": 1, "channels": 0, "frequency": 10000, "q": 0, "gain": 0.0, "color": 0}, {"type": 3, "channels": 0, "frequency": 20, "q": 0.4, "gain": 11.1, "color": -5863292}, {"type": 3, "channels": 0, "frequency": 20, "q": 5.0, "gain": 1.1, "color": -1703336}, {"type": 3, "channels": 0, "frequency": 170, "q": 2.4, "gain": -2.1, "color": -3003903}, {"type": 3, "channels": 0, "frequency": 400, "q": 4.8, "gain": -1.1, "color": -3238981}, {"type": 3, "channels": 0, "frequency": 1800, "q": 1.5, "gain": 2.0, "color": -14975005}, {"type": 3, "channels": 0, "frequency": 2400, "q": 4.2, "gain": -0.8, "color": -163378}, {"type": 3, "channels": 0, "frequency": 3700, "q": 3.5, "gain": 2.0, "color": -15207078}, {"type": 3, "channels": 0, "frequency": 4300, "q": 5.0, "gain": -2.5, "color": -14333042}, {"type": 3, "channels": 0, "frequency": 5900, "q": 1.8, "gain": -2.5, "color": -12691350}, {"type": 3, "channels": 0, "frequency": 7500, "q": 5.0, "gain": 1.0, "color": -6867683}, {"type": 3, "channels": 0, "frequency": 7900, "q": 5.0, "gain": 2.2, "color": -14757967}, {"type": 3, "channels": 0, "frequency": 10000, "q": 2.5, "gain": -8.2, "color": -1819753}, {"type": 3, "channels": 0, "frequency": 12000, "q": 5.0, "gain": 6.1, "color": -13951121}, {"type": 3, "channels": 0, "frequency": 15000, "q": 5.0, "gain": 5.3, "color": -8900537}]}]