[{"name": "EQ to Salnotes Zero (AVG)", "preamp": 0.0, "parametric": true, "bands": [{"type": 0, "channels": 0, "frequency": 90, "q": 0, "gain": 0.0, "color": 0}, {"type": 1, "channels": 0, "frequency": 10000, "q": 0, "gain": 0.0, "color": 0}, {"type": 3, "channels": 0, "frequency": 40, "q": 0.3, "gain": -2.9, "color": -15126435}, {"type": 3, "channels": 0, "frequency": 63, "q": 2.0, "gain": -0.7, "color": -8290976}, {"type": 3, "channels": 0, "frequency": 130, "q": 4.8, "gain": -0.9, "color": -6185841}, {"type": 3, "channels": 0, "frequency": 190, "q": 1.9, "gain": 0.9, "color": -13089822}, {"type": 3, "channels": 0, "frequency": 360, "q": 3.4, "gain": -0.9, "color": -4783860}, {"type": 3, "channels": 0, "frequency": 680, "q": 2.8, "gain": -0.6, "color": -3695882}, {"type": 3, "channels": 0, "frequency": 1800, "q": 2.0, "gain": 1.9, "color": -1774681}, {"type": 3, "channels": 0, "frequency": 3800, "q": 1.6, "gain": 2.2, "color": -15002602}, {"type": 3, "channels": 0, "frequency": 5500, "q": 2.3, "gain": -5.1, "color": -2990069}, {"type": 3, "channels": 0, "frequency": 9300, "q": 4.8, "gain": -7.1, "color": -7267734}, {"type": 3, "channels": 0, "frequency": 11000, "q": 5.0, "gain": 8.5, "color": -4045348}]}]