[{"name": "EQ to AKG K371 (AVG)", "preamp": 0.0, "parametric": true, "bands": [{"type": 0, "channels": 0, "frequency": 90, "q": 0, "gain": 0.0, "color": 0}, {"type": 1, "channels": 0, "frequency": 10000, "q": 0, "gain": 0.0, "color": 0}, {"type": 3, "channels": 0, "frequency": 20, "q": 1.4, "gain": -0.5, "color": -304052}, {"type": 3, "channels": 0, "frequency": 64, "q": 1.1, "gain": -3.7, "color": -5431309}, {"type": 3, "channels": 0, "frequency": 130, "q": 4.4, "gain": 0.9, "color": -6878493}, {"type": 3, "channels": 0, "frequency": 670, "q": 1.7, "gain": 1.3, "color": -393894}, {"type": 3, "channels": 0, "frequency": 1900, "q": 1.1, "gain": -1.4, "color": -6006564}, {"type": 3, "channels": 0, "frequency": 2400, "q": 4.1, "gain": -1.4, "color": -11798980}, {"type": 3, "channels": 0, "frequency": 4100, "q": 2.5, "gain": 2.8, "color": -4998424}, {"type": 3, "channels": 0, "frequency": 5000, "q": 5.0, "gain": -3.4, "color": -7164531}, {"type": 3, "channels": 0, "frequency": 6700, "q": 5.0, "gain": -3.3, "color": -6195020}, {"type": 3, "channels": 0, "frequency": 7700, "q": 5.0, "gain": 2.9, "color": -14949322}, {"type": 3, "channels": 0, "frequency": 9200, "q": 3.1, "gain": 7.3, "color": -10603890}, {"type": 3, "channels": 0, "frequency": 10000, "q": 5.0, "gain": 3.9, "color": -10971029}, {"type": 3, "channels": 0, "frequency": 12000, "q": 5.0, "gain": -8.7, "color": -13531966}, {"type": 3, "channels": 0, "frequency": 17000, "q": 2.0, "gain": -14.8, "color": -1806305}]}]