[{"name": "EQ to Truthear ZeroRED (AVG)", "preamp": 0.0, "parametric": true, "bands": [{"type": 0, "channels": 0, "frequency": 90, "q": 0, "gain": 0.0, "color": 0}, {"type": 1, "channels": 0, "frequency": 10000, "q": 0, "gain": 0.0, "color": 0}, {"type": 3, "channels": 0, "frequency": 20, "q": 1.0, "gain": -2.9, "color": -281369}, {"type": 3, "channels": 0, "frequency": 190, "q": 2.9, "gain": -2.9, "color": -3493566}, {"type": 3, "channels": 0, "frequency": 360, "q": 4.4, "gain": 1.0, "color": -8343885}, {"type": 3, "channels": 0, "frequency": 450, "q": 3.9, "gain": -1.6, "color": -10565114}, {"type": 3, "channels": 0, "frequency": 2900, "q": 3.3, "gain": -1.5, "color": -2809667}, {"type": 3, "channels": 0, "frequency": 3300, "q": 1.2, "gain": 2.9, "color": -12333270}, {"type": 3, "channels": 0, "frequency": 4500, "q": 5.0, "gain": -0.8, "color": -5401963}, {"type": 3, "channels": 0, "frequency": 6400, "q": 2.9, "gain": -6.0, "color": -12230956}, {"type": 3, "channels": 0, "frequency": 7100, "q": 5.0, "gain": -1.5, "color": -4861354}, {"type": 3, "channels": 0, "frequency": 8100, "q": 4.6, "gain": 4.8, "color": -7874812}, {"type": 3, "channels": 0, "frequency": 9700, "q": 4.7, "gain": -7.1, "color": -8645373}, {"type": 3, "channels": 0, "frequency": 12000, "q": 3.0, "gain": 4.6, "color": -7658865}, {"type": 3, "channels": 0, "frequency": 18000, "q": 2.5, "gain": -12.5, "color": -14802721}, {"type": 3, "channels": 0, "frequency": 19000, "q": 3.2, "gain": -11.3, "color": -9611403}]}]