[{"name": "EQ to Audeze EL-8 (AVG)", "preamp": 0.0, "parametric": true, "bands": [{"type": 0, "channels": 0, "frequency": 90, "q": 0, "gain": 0.0, "color": 0}, {"type": 1, "channels": 0, "frequency": 10000, "q": 0, "gain": 0.0, "color": 0}, {"type": 3, "channels": 0, "frequency": 20, "q": 0.4, "gain": -10.3, "color": -10984207}, {"type": 3, "channels": 0, "frequency": 38, "q": 3.0, "gain": 1.9, "color": -14579786}, {"type": 3, "channels": 0, "frequency": 72, "q": 2.8, "gain": -0.7, "color": -2793190}, {"type": 3, "channels": 0, "frequency": 140, "q": 2.8, "gain": -1.4, "color": -10151878}, {"type": 3, "channels": 0, "frequency": 230, "q": 4.1, "gain": 1.0, "color": -5781745}, {"type": 3, "channels": 0, "frequency": 420, "q": 2.4, "gain": 1.0, "color": -3038427}, {"type": 3, "channels": 0, "frequency": 510, "q": 0.5, "gain": 1.4, "color": -11060342}, {"type": 3, "channels": 0, "frequency": 930, "q": 4.2, "gain": 1.0, "color": -2887826}, {"type": 3, "channels": 0, "frequency": 1600, "q": 4.3, "gain": -0.9, "color": -16335660}, {"type": 3, "channels": 0, "frequency": 2300, "q": 2.3, "gain": 3.9, "color": -9004841}, {"type": 3, "channels": 0, "frequency": 3500, "q": 2.6, "gain": 5.4, "color": -440046}, {"type": 3, "channels": 0, "frequency": 5600, "q": 1.0, "gain": -11.8, "color": -16201128}, {"type": 3, "channels": 0, "frequency": 7200, "q": 5.0, "gain": -7.4, "color": -5972207}, {"type": 3, "channels": 0, "frequency": 10000, "q": 4.2, "gain": 8.6, "color": -1804060}]}]