[{"name": "EQ to Sennheiser HE-1 (AVG)", "preamp": 0.0, "parametric": true, "bands": [{"type": 0, "channels": 0, "frequency": 90, "q": 0, "gain": 0.0, "color": 0}, {"type": 1, "channels": 0, "frequency": 10000, "q": 0, "gain": 0.0, "color": 0}, {"type": 3, "channels": 0, "frequency": 20, "q": 0.3, "gain": -5.7, "color": -12125204}, {"type": 3, "channels": 0, "frequency": 21, "q": 2.5, "gain": -2.2, "color": -4640346}, {"type": 3, "channels": 0, "frequency": 46, "q": 2.4, "gain": 2.5, "color": -12597102}, {"type": 3, "channels": 0, "frequency": 100, "q": 3.3, "gain": -0.5, "color": -14635513}, {"type": 3, "channels": 0, "frequency": 200, "q": 1.8, "gain": -2.0, "color": -3001880}, {"type": 3, "channels": 0, "frequency": 470, "q": 3.5, "gain": 1.0, "color": -7771317}, {"type": 3, "channels": 0, "frequency": 840, "q": 1.0, "gain": 2.3, "color": -11813770}, {"type": 3, "channels": 0, "frequency": 1800, "q": 1.4, "gain": -7.0, "color": -15833980}, {"type": 3, "channels": 0, "frequency": 3100, "q": 2.5, "gain": 5.3, "color": -339492}, {"type": 3, "channels": 0, "frequency": 4400, "q": 4.3, "gain": -6.1, "color": -16293176}, {"type": 3, "channels": 0, "frequency": 8800, "q": 1.9, "gain": 10.5, "color": -15167155}, {"type": 3, "channels": 0, "frequency": 10000, "q": 4.2, "gain": 3.8, "color": -5851439}, {"type": 3, "channels": 0, "frequency": 11000, "q": 5.0, "gain": -3.2, "color": -10485890}, {"type": 3, "channels": 0, "frequency": 17000, "q": 2.1, "gain": -18.0, "color": -8692165}]}]