[{"name": "EQ to Salnotes Zero (L)", "preamp": 0.0, "parametric": true, "bands": [{"type": 0, "channels": 0, "frequency": 90, "q": 0, "gain": 0.0, "color": 0}, {"type": 1, "channels": 0, "frequency": 10000, "q": 0, "gain": 0.0, "color": 0}, {"type": 3, "channels": 0, "frequency": 20, "q": 0.2, "gain": -6.4, "color": -4184527}, {"type": 3, "channels": 0, "frequency": 68, "q": 1.9, "gain": 0.7, "color": -595501}, {"type": 3, "channels": 0, "frequency": 120, "q": 2.9, "gain": -1.2, "color": -311903}, {"type": 3, "channels": 0, "frequency": 210, "q": 3.8, "gain": -1.2, "color": -272088}, {"type": 3, "channels": 0, "frequency": 280, "q": 4.1, "gain": 1.1, "color": -3704305}, {"type": 3, "channels": 0, "frequency": 290, "q": 2.0, "gain": -2.9, "color": -2100658}, {"type": 3, "channels": 0, "frequency": 390, "q": 4.5, "gain": -1.7, "color": -6069133}, {"type": 3, "channels": 0, "frequency": 1100, "q": 1.1, "gain": 0.7, "color": -11427433}, {"type": 3, "channels": 0, "frequency": 2100, "q": 3.8, "gain": -2.2, "color": -6087151}, {"type": 3, "channels": 0, "frequency": 3300, "q": 2.4, "gain": 4.5, "color": -15430510}, {"type": 3, "channels": 0, "frequency": 4600, "q": 5.0, "gain": -2.2, "color": -8263547}, {"type": 3, "channels": 0, "frequency": 7600, "q": 5.0, "gain": 2.9, "color": -8327213}, {"type": 3, "channels": 0, "frequency": 11000, "q": 4.6, "gain": 7.7, "color": -2537823}, {"type": 3, "channels": 0, "frequency": 18000, "q": 1.5, "gain": -12.9, "color": -8203218}]}]