[{"name": "EQ to Audeze LCD-5 (AVG)", "preamp": 0.0, "parametric": true, "bands": [{"type": 0, "channels": 0, "frequency": 90, "q": 0, "gain": 0.0, "color": 0}, {"type": 1, "channels": 0, "frequency": 10000, "q": 0, "gain": 0.0, "color": 0}, {"type": 3, "channels": 0, "frequency": 20, "q": 5.0, "gain": 0.7, "color": -13623814}, {"type": 3, "channels": 0, "frequency": 22, "q": 1.5, "gain": 5.9, "color": -8841227}, {"type": 3, "channels": 0, "frequency": 39, "q": 2.3, "gain": 0.7, "color": -11853964}, {"type": 3, "channels": 0, "frequency": 63, "q": 2.7, "gain": 1.0, "color": -2733293}, {"type": 3, "channels": 0, "frequency": 140, "q": 0.8, "gain": -1.6, "color": -16507689}, {"type": 3, "channels": 0, "frequency": 930, "q": 1.1, "gain": 1.0, "color": -1578184}, {"type": 3, "channels": 0, "frequency": 1600, "q": 3.0, "gain": 0.9, "color": -4066918}, {"type": 3, "channels": 0, "frequency": 6200, "q": 2.4, "gain": -2.8, "color": -11193942}, {"type": 3, "channels": 0, "frequency": 12000, "q": 0.6, "gain": -2.9, "color": -1634597}]}]