[{"name": "EQ to Simgot EW100P (AVG)", "preamp": 0.0, "parametric": true, "bands": [{"type": 0, "channels": 0, "frequency": 90, "q": 0, "gain": 0.0, "color": 0}, {"type": 1, "channels": 0, "frequency": 10000, "q": 0, "gain": 0.0, "color": 0}, {"type": 3, "channels": 0, "frequency": 21, "q": 0.5, "gain": 13.3, "color": -7973053}, {"type": 3, "channels": 0, "frequency": 62, "q": 2.5, "gain": 0.9, "color": -9985451}, {"type": 3, "channels": 0, "frequency": 140, "q": 2.1, "gain": -2.9, "color": -8053871}, {"type": 3, "channels": 0, "frequency": 390, "q": 2.1, "gain": -3.2, "color": -8530620}, {"type": 3, "channels": 0, "frequency": 490, "q": 5.0, "gain": 0.7, "color": -5209608}, {"type": 3, "channels": 0, "frequency": 790, "q": 2.7, "gain": -1.0, "color": -11567349}, {"type": 3, "channels": 0, "frequency": 1800, "q": 1.8, "gain": 1.2, "color": -7877022}, {"type": 3, "channels": 0, "frequency": 3300, "q": 3.3, "gain": -1.6, "color": -14529651}, {"type": 3, "channels": 0, "frequency": 5000, "q": 2.5, "gain": 4.6, "color": -15336231}, {"type": 3, "channels": 0, "frequency": 6600, "q": 2.1, "gain": 2.0, "color": -14136383}, {"type": 3, "channels": 0, "frequency": 9800, "q": 1.6, "gain": -8.4, "color": -6274004}, {"type": 3, "channels": 0, "frequency": 12000, "q": 4.6, "gain": 7.0, "color": -6833099}, {"type": 3, "channels": 0, "frequency": 15000, "q": 5.0, "gain": 6.1, "color": -8686413}, {"type": 3, "channels": 0, "frequency": 17000, "q": 4.7, "gain": -3.6, "color": -1793079}]}]