[{"name": "EQ to Samsung GalaxyBuds2Pro (AVG)", "preamp": 0.0, "parametric": true, "bands": [{"type": 0, "channels": 0, "frequency": 90, "q": 0, "gain": 0.0, "color": 0}, {"type": 1, "channels": 0, "frequency": 10000, "q": 0, "gain": 0.0, "color": 0}, {"type": 3, "channels": 0, "frequency": 20, "q": 2.3, "gain": 0.6, "color": -2671390}, {"type": 3, "channels": 0, "frequency": 24, "q": 0.3, "gain": 8.1, "color": -9734259}, {"type": 3, "channels": 0, "frequency": 50, "q": 1.9, "gain": -0.6, "color": -3954129}, {"type": 3, "channels": 0, "frequency": 380, "q": 1.4, "gain": 3.3, "color": -3729946}, {"type": 3, "channels": 0, "frequency": 880, "q": 3.0, "gain": -0.9, "color": -7370614}, {"type": 3, "channels": 0, "frequency": 1900, "q": 2.4, "gain": -6.4, "color": -4948208}, {"type": 3, "channels": 0, "frequency": 2700, "q": 4.1, "gain": 2.6, "color": -7466279}, {"type": 3, "channels": 0, "frequency": 4400, "q": 2.6, "gain": 5.2, "color": -6759903}, {"type": 3, "channels": 0, "frequency": 6200, "q": 4.6, "gain": -3.4, "color": -840349}, {"type": 3, "channels": 0, "frequency": 8000, "q": 2.0, "gain": -10.3, "color": -11798027}, {"type": 3, "channels": 0, "frequency": 9800, "q": 4.3, "gain": -1.6, "color": -15449619}, {"type": 3, "channels": 0, "frequency": 13000, "q": 1.4, "gain": 18.0, "color": -1931981}]}]