[{"name": "EQ to [APROX]Moondrop Blessing2 (AVG)", "preamp": 0.0, "parametric": true, "bands": [{"type": 0, "channels": 0, "frequency": 90, "q": 0, "gain": 0.0, "color": 0}, {"type": 1, "channels": 0, "frequency": 10000, "q": 0, "gain": 0.0, "color": 0}, {"type": 3, "channels": 0, "frequency": 21, "q": 3.9, "gain": 0.6, "color": -12311073}, {"type": 3, "channels": 0, "frequency": 100, "q": 0.5, "gain": -1.7, "color": -8978049}, {"type": 3, "channels": 0, "frequency": 130, "q": 3.5, "gain": -1.0, "color": -15104683}, {"type": 3, "channels": 0, "frequency": 190, "q": 3.4, "gain": 1.6, "color": -7613556}, {"type": 3, "channels": 0, "frequency": 320, "q": 2.2, "gain": -0.6, "color": -15187550}, {"type": 3, "channels": 0, "frequency": 730, "q": 1.1, "gain": 2.0, "color": -2050066}, {"type": 3, "channels": 0, "frequency": 1800, "q": 2.6, "gain": -3.5, "color": -5657820}, {"type": 3, "channels": 0, "frequency": 2700, "q": 4.0, "gain": 1.5, "color": -15570396}, {"type": 3, "channels": 0, "frequency": 3500, "q": 5.0, "gain": -1.8, "color": -5623560}, {"type": 3, "channels": 0, "frequency": 4500, "q": 3.3, "gain": 2.7, "color": -9472921}, {"type": 3, "channels": 0, "frequency": 6500, "q": 5.0, "gain": -2.9, "color": -15818706}, {"type": 3, "channels": 0, "frequency": 8500, "q": 2.3, "gain": -2.5, "color": -3376628}, {"type": 3, "channels": 0, "frequency": 13000, "q": 4.8, "gain": 5.5, "color": -6882652}, {"type": 3, "channels": 0, "frequency": 19000, "q": 0.7, "gain": 15.1, "color": -7326189}]}]