[{"name": "EQ to Focal Utopia (AVG)", "preamp": 0.0, "parametric": true, "bands": [{"type": 0, "channels": 0, "frequency": 90, "q": 0, "gain": 0.0, "color": 0}, {"type": 1, "channels": 0, "frequency": 10000, "q": 0, "gain": 0.0, "color": 0}, {"type": 3, "channels": 0, "frequency": 20, "q": 2.5, "gain": -3.4, "color": -194612}, {"type": 3, "channels": 0, "frequency": 26, "q": 0.5, "gain": -7.7, "color": -15241296}, {"type": 3, "channels": 0, "frequency": 130, "q": 4.0, "gain": 0.9, "color": -13609886}, {"type": 3, "channels": 0, "frequency": 170, "q": 3.4, "gain": -0.8, "color": -15431757}, {"type": 3, "channels": 0, "frequency": 510, "q": 2.3, "gain": 0.7, "color": -12033680}, {"type": 3, "channels": 0, "frequency": 2000, "q": 2.6, "gain": -4.9, "color": -1030976}, {"type": 3, "channels": 0, "frequency": 3200, "q": 2.3, "gain": 4.3, "color": -4395281}, {"type": 3, "channels": 0, "frequency": 4800, "q": 4.4, "gain": -3.6, "color": -16517829}, {"type": 3, "channels": 0, "frequency": 5100, "q": 4.0, "gain": -1.0, "color": -2805882}, {"type": 3, "channels": 0, "frequency": 5200, "q": 5.0, "gain": -1.8, "color": -3276180}, {"type": 3, "channels": 0, "frequency": 6000, "q": 5.0, "gain": 7.3, "color": -13515505}, {"type": 3, "channels": 0, "frequency": 8100, "q": 5.0, "gain": 5.0, "color": -10681378}, {"type": 3, "channels": 0, "frequency": 9900, "q": 4.3, "gain": -3.9, "color": -5707194}, {"type": 3, "channels": 0, "frequency": 12000, "q": 5.0, "gain": 6.3, "color": -6352684}]}]