[{"name": "EQ to Kinera URD (AVG)", "preamp": 0.0, "parametric": true, "bands": [{"type": 0, "channels": 0, "frequency": 90, "q": 0, "gain": 0.0, "color": 0}, {"type": 1, "channels": 0, "frequency": 10000, "q": 0, "gain": 0.0, "color": 0}, {"type": 3, "channels": 0, "frequency": 20, "q": 1.1, "gain": 6.3, "color": -5867407}, {"type": 3, "channels": 0, "frequency": 47, "q": 4.1, "gain": -1.4, "color": -1534391}, {"type": 3, "channels": 0, "frequency": 88, "q": 2.3, "gain": 0.4, "color": -5752264}, {"type": 3, "channels": 0, "frequency": 180, "q": 2.8, "gain": 1.4, "color": -4873455}, {"type": 3, "channels": 0, "frequency": 520, "q": 1.2, "gain": -1.9, "color": -8345775}, {"type": 3, "channels": 0, "frequency": 1700, "q": 1.5, "gain": 5.8, "color": -16446719}, {"type": 3, "channels": 0, "frequency": 2300, "q": 4.7, "gain": 1.6, "color": -7274873}, {"type": 3, "channels": 0, "frequency": 3200, "q": 3.0, "gain": -4.7, "color": -775539}, {"type": 3, "channels": 0, "frequency": 4700, "q": 3.0, "gain": 8.0, "color": -4805167}, {"type": 3, "channels": 0, "frequency": 6200, "q": 5.0, "gain": -4.1, "color": -3816446}, {"type": 3, "channels": 0, "frequency": 7300, "q": 1.1, "gain": -7.2, "color": -3693451}, {"type": 3, "channels": 0, "frequency": 8000, "q": 5.0, "gain": 2.4, "color": -8695751}, {"type": 3, "channels": 0, "frequency": 13000, "q": 4.1, "gain": -8.0, "color": -6834218}, {"type": 3, "channels": 0, "frequency": 16000, "q": 3.9, "gain": 4.3, "color": -12204665}]}]