[{"name": "EQ to Sennheiser HD 580 Precision (AVG)", "preamp": 0.0, "parametric": true, "bands": [{"type": 0, "channels": 0, "frequency": 90, "q": 0, "gain": 0.0, "color": 0}, {"type": 1, "channels": 0, "frequency": 10000, "q": 0, "gain": 0.0, "color": 0}, {"type": 3, "channels": 0, "frequency": 22, "q": 0.6, "gain": -6.0, "color": -8360770}, {"type": 3, "channels": 0, "frequency": 28, "q": 4.3, "gain": 0.9, "color": -16612593}, {"type": 3, "channels": 0, "frequency": 39, "q": 2.7, "gain": -1.0, "color": -13168787}, {"type": 3, "channels": 0, "frequency": 110, "q": 1.0, "gain": 1.8, "color": -2227058}, {"type": 3, "channels": 0, "frequency": 580, "q": 1.7, "gain": -0.5, "color": -11669847}, {"type": 3, "channels": 0, "frequency": 1300, "q": 0.4, "gain": -3.5, "color": -5371394}, {"type": 3, "channels": 0, "frequency": 1600, "q": 2.5, "gain": 1.9, "color": -6622216}, {"type": 3, "channels": 0, "frequency": 2300, "q": 4.3, "gain": -1.7, "color": -14704589}, {"type": 3, "channels": 0, "frequency": 5800, "q": 3.7, "gain": -3.9, "color": -4125539}, {"type": 3, "channels": 0, "frequency": 6300, "q": 0.7, "gain": 10.6, "color": -4152297}, {"type": 3, "channels": 0, "frequency": 7300, "q": 3.9, "gain": 8.6, "color": -5312676}, {"type": 3, "channels": 0, "frequency": 9600, "q": 5.0, "gain": -11.0, "color": -1331989}, {"type": 3, "channels": 0, "frequency": 13000, "q": 5.0, "gain": 3.9, "color": -2908931}, {"type": 3, "channels": 0, "frequency": 17000, "q": 5.0, "gain": 6.6, "color": -628563}]}]