[{"name": "EQ to Truthear ZeroRED (AVG)", "preamp": 0.0, "parametric": true, "bands": [{"type": 0, "channels": 0, "frequency": 90, "q": 0, "gain": 0.0, "color": 0}, {"type": 1, "channels": 0, "frequency": 10000, "q": 0, "gain": 0.0, "color": 0}, {"type": 3, "channels": 0, "frequency": 22, "q": 0.4, "gain": 5.3, "color": -5449190}, {"type": 3, "channels": 0, "frequency": 160, "q": 1.5, "gain": -3.4, "color": -11890304}, {"type": 3, "channels": 0, "frequency": 250, "q": 5.0, "gain": 2.1, "color": -14369766}, {"type": 3, "channels": 0, "frequency": 320, "q": 3.3, "gain": -2.2, "color": -2567830}, {"type": 3, "channels": 0, "frequency": 1600, "q": 0.4, "gain": 2.5, "color": -13536745}, {"type": 3, "channels": 0, "frequency": 2800, "q": 2.7, "gain": -6.0, "color": -13926220}, {"type": 3, "channels": 0, "frequency": 4000, "q": 4.3, "gain": 1.2, "color": -1812562}, {"type": 3, "channels": 0, "frequency": 6000, "q": 2.4, "gain": -4.9, "color": -9548274}, {"type": 3, "channels": 0, "frequency": 8200, "q": 5.0, "gain": 2.3, "color": -6091128}, {"type": 3, "channels": 0, "frequency": 8400, "q": 1.5, "gain": -1.0, "color": -13740202}, {"type": 3, "channels": 0, "frequency": 11000, "q": 4.0, "gain": 4.3, "color": -13713051}, {"type": 3, "channels": 0, "frequency": 14000, "q": 4.9, "gain": -3.0, "color": -8219143}, {"type": 3, "channels": 0, "frequency": 16000, "q": 3.5, "gain": 5.0, "color": -12371936}, {"type": 3, "channels": 0, "frequency": 18000, "q": 2.2, "gain": -5.3, "color": -2471443}]}]