[{"name": "EQ to Symphonium Helios (Azla Sedna Tips) (AVG)", "preamp": 0.0, "parametric": true, "bands": [{"type": 0, "channels": 0, "frequency": 90, "q": 0, "gain": 0.0, "color": 0}, {"type": 1, "channels": 0, "frequency": 10000, "q": 0, "gain": 0.0, "color": 0}, {"type": 3, "channels": 0, "frequency": 21, "q": 3.4, "gain": -1.9, "color": -7144204}, {"type": 3, "channels": 0, "frequency": 84, "q": 0.3, "gain": -4.2, "color": -8914418}, {"type": 3, "channels": 0, "frequency": 100, "q": 2.9, "gain": -1.7, "color": -6930787}, {"type": 3, "channels": 0, "frequency": 140, "q": 4.1, "gain": 3.1, "color": -6586469}, {"type": 3, "channels": 0, "frequency": 580, "q": 1.4, "gain": 2.5, "color": -9355067}, {"type": 3, "channels": 0, "frequency": 2500, "q": 4.0, "gain": -0.8, "color": -14361529}, {"type": 3, "channels": 0, "frequency": 4400, "q": 1.7, "gain": -2.1, "color": -10670511}, {"type": 3, "channels": 0, "frequency": 5000, "q": 5.0, "gain": -3.3, "color": -6447786}, {"type": 3, "channels": 0, "frequency": 5500, "q": 5.0, "gain": 2.6, "color": -1806057}, {"type": 3, "channels": 0, "frequency": 6100, "q": 3.2, "gain": 2.4, "color": -2724751}, {"type": 3, "channels": 0, "frequency": 7600, "q": 2.1, "gain": 1.2, "color": -9917780}, {"type": 3, "channels": 0, "frequency": 9600, "q": 3.9, "gain": -6.8, "color": -7526938}, {"type": 3, "channels": 0, "frequency": 12000, "q": 5.0, "gain": 7.3, "color": -8742097}, {"type": 3, "channels": 0, "frequency": 15000, "q": 4.2, "gain": -8.6, "color": -6468689}]}]