[{"name": "EQ to Thieaudio Monarch MkII (AVG)", "preamp": 0.0, "parametric": true, "bands": [{"type": 0, "channels": 0, "frequency": 90, "q": 0, "gain": 0.0, "color": 0}, {"type": 1, "channels": 0, "frequency": 10000, "q": 0, "gain": 0.0, "color": 0}, {"type": 3, "channels": 0, "frequency": 26, "q": 0.6, "gain": 2.5, "color": -15614682}, {"type": 3, "channels": 0, "frequency": 140, "q": 2.0, "gain": -2.9, "color": -13193491}, {"type": 3, "channels": 0, "frequency": 240, "q": 3.6, "gain": -0.9, "color": -11181426}, {"type": 3, "channels": 0, "frequency": 770, "q": 0.9, "gain": 1.7, "color": -15446439}, {"type": 3, "channels": 0, "frequency": 2000, "q": 1.6, "gain": -2.9, "color": -3712691}, {"type": 3, "channels": 0, "frequency": 3600, "q": 3.3, "gain": 2.1, "color": -14453999}, {"type": 3, "channels": 0, "frequency": 4400, "q": 5.0, "gain": -4.8, "color": -11637808}, {"type": 3, "channels": 0, "frequency": 5300, "q": 5.0, "gain": 1.5, "color": -7144044}, {"type": 3, "channels": 0, "frequency": 6000, "q": 1.2, "gain": 1.9, "color": -4476562}, {"type": 3, "channels": 0, "frequency": 8200, "q": 5.0, "gain": -4.7, "color": -15225129}, {"type": 3, "channels": 0, "frequency": 10000, "q": 4.9, "gain": 5.6, "color": -1314559}, {"type": 3, "channels": 0, "frequency": 11000, "q": 3.1, "gain": -3.8, "color": -11678310}]}]