[{"name": "EQ to Truthear x Crinacle Red (AVG)", "preamp": 0.0, "parametric": true, "bands": [{"type": 0, "channels": 0, "frequency": 90, "q": 0, "gain": 0.0, "color": 0}, {"type": 1, "channels": 0, "frequency": 10000, "q": 0, "gain": 0.0, "color": 0}, {"type": 3, "channels": 0, "frequency": 20, "q": 5.0, "gain": 0.8, "color": -6356778}, {"type": 3, "channels": 0, "frequency": 21, "q": 0.8, "gain": 11.2, "color": -15336881}, {"type": 3, "channels": 0, "frequency": 70, "q": 0.5, "gain": 1.0, "color": -2900266}, {"type": 3, "channels": 0, "frequency": 77, "q": 4.9, "gain": 2.8, "color": -10771895}, {"type": 3, "channels": 0, "frequency": 100, "q": 5.0, "gain": -1.1, "color": -9230067}, {"type": 3, "channels": 0, "frequency": 130, "q": 2.4, "gain": -2.6, "color": -2797701}, {"type": 3, "channels": 0, "frequency": 160, "q": 3.8, "gain": -1.1, "color": -13888007}, {"type": 3, "channels": 0, "frequency": 230, "q": 2.3, "gain": 2.5, "color": -207610}, {"type": 3, "channels": 0, "frequency": 410, "q": 2.4, "gain": -1.5, "color": -13739667}, {"type": 3, "channels": 0, "frequency": 3100, "q": 0.4, "gain": 3.4, "color": -8339430}, {"type": 3, "channels": 0, "frequency": 3700, "q": 4.0, "gain": 7.1, "color": -16479245}, {"type": 3, "channels": 0, "frequency": 4400, "q": 1.9, "gain": 2.1, "color": -3035076}, {"type": 3, "channels": 0, "frequency": 19000, "q": 0.1, "gain": -12.3, "color": -3585466}]}]