[{"name": "EQ to Audeze LCD-5 (AVG)", "preamp": 0.0, "parametric": true, "bands": [{"type": 0, "channels": 0, "frequency": 90, "q": 0, "gain": 0.0, "color": 0}, {"type": 1, "channels": 0, "frequency": 10000, "q": 0, "gain": 0.0, "color": 0}, {"type": 3, "channels": 0, "frequency": 20, "q": 1.7, "gain": 3.1, "color": -7237092}, {"type": 3, "channels": 0, "frequency": 41, "q": 1.7, "gain": -0.8, "color": -5307078}, {"type": 3, "channels": 0, "frequency": 88, "q": 1.1, "gain": -1.8, "color": -10523515}, {"type": 3, "channels": 0, "frequency": 250, "q": 2.1, "gain": 2.2, "color": -14664055}, {"type": 3, "channels": 0, "frequency": 640, "q": 2.0, "gain": 1.0, "color": -7712503}, {"type": 3, "channels": 0, "frequency": 1200, "q": 3.3, "gain": -3.1, "color": -4430878}, {"type": 3, "channels": 0, "frequency": 1400, "q": 4.7, "gain": -4.1, "color": -4592198}, {"type": 3, "channels": 0, "frequency": 2800, "q": 5.0, "gain": 3.7, "color": -10772992}, {"type": 3, "channels": 0, "frequency": 3000, "q": 2.4, "gain": 16.1, "color": -12980296}, {"type": 3, "channels": 0, "frequency": 4200, "q": 3.9, "gain": 4.6, "color": -7823255}, {"type": 3, "channels": 0, "frequency": 6200, "q": 5.0, "gain": -2.7, "color": -10899853}, {"type": 3, "channels": 0, "frequency": 7500, "q": 0.9, "gain": -6.6, "color": -3299448}, {"type": 3, "channels": 0, "frequency": 13000, "q": 5.0, "gain": -5.4, "color": -11060539}, {"type": 3, "channels": 0, "frequency": 18000, "q": 1.8, "gain": 9.2, "color": -14781921}]}]