[{"name": "EQ to Truthear ZeroRED (AVG)", "preamp": 0.0, "parametric": true, "bands": [{"type": 0, "channels": 0, "frequency": 90, "q": 0, "gain": 0.0, "color": 0}, {"type": 1, "channels": 0, "frequency": 10000, "q": 0, "gain": 0.0, "color": 0}, {"type": 3, "channels": 0, "frequency": 75, "q": 0.5, "gain": 1.9, "color": -6190075}, {"type": 3, "channels": 0, "frequency": 100, "q": 4.8, "gain": 1.0, "color": -12358678}, {"type": 3, "channels": 0, "frequency": 130, "q": 4.7, "gain": -1.7, "color": -11074540}, {"type": 3, "channels": 0, "frequency": 160, "q": 1.9, "gain": -2.6, "color": -10125191}, {"type": 3, "channels": 0, "frequency": 200, "q": 4.9, "gain": -1.3, "color": -12401953}, {"type": 3, "channels": 0, "frequency": 550, "q": 0.7, "gain": 1.0, "color": -9811675}, {"type": 3, "channels": 0, "frequency": 2300, "q": 2.1, "gain": -1.2, "color": -7419467}, {"type": 3, "channels": 0, "frequency": 3500, "q": 2.9, "gain": 1.5, "color": -13400748}, {"type": 3, "channels": 0, "frequency": 5200, "q": 2.3, "gain": -3.1, "color": -1782941}, {"type": 3, "channels": 0, "frequency": 7400, "q": 4.9, "gain": -1.6, "color": -1717510}, {"type": 3, "channels": 0, "frequency": 9100, "q": 3.9, "gain": 6.7, "color": -8730311}, {"type": 3, "channels": 0, "frequency": 12000, "q": 3.1, "gain": -8.0, "color": -4660612}, {"type": 3, "channels": 0, "frequency": 16000, "q": 5.0, "gain": 5.3, "color": -8586008}, {"type": 3, "channels": 0, "frequency": 19000, "q": 1.2, "gain": -7.2, "color": -1703197}]}]