[{"name": "EQ to Nightjar Singularity (Coreir Tips) (AVG)", "preamp": 0.0, "parametric": true, "bands": [{"type": 0, "channels": 0, "frequency": 90, "q": 0, "gain": 0.0, "color": 0}, {"type": 1, "channels": 0, "frequency": 10000, "q": 0, "gain": 0.0, "color": 0}, {"type": 3, "channels": 0, "frequency": 24, "q": 0.2, "gain": 4.0, "color": -3465543}, {"type": 3, "channels": 0, "frequency": 94, "q": 3.5, "gain": 2.0, "color": -13319015}, {"type": 3, "channels": 0, "frequency": 130, "q": 3.6, "gain": -2.5, "color": -1904712}, {"type": 3, "channels": 0, "frequency": 350, "q": 0.3, "gain": 1.2, "color": -6529749}, {"type": 3, "channels": 0, "frequency": 350, "q": 3.0, "gain": 0.9, "color": -2541891}, {"type": 3, "channels": 0, "frequency": 590, "q": 2.3, "gain": -1.6, "color": -9822033}, {"type": 3, "channels": 0, "frequency": 3100, "q": 1.7, "gain": 0.8, "color": -9256737}, {"type": 3, "channels": 0, "frequency": 6000, "q": 1.2, "gain": -4.0, "color": -1898521}, {"type": 3, "channels": 0, "frequency": 7400, "q": 4.6, "gain": -1.6, "color": -9633119}, {"type": 3, "channels": 0, "frequency": 8500, "q": 4.3, "gain": 2.4, "color": -11827487}, {"type": 3, "channels": 0, "frequency": 9500, "q": 4.0, "gain": 1.9, "color": -7468078}, {"type": 3, "channels": 0, "frequency": 10000, "q": 3.6, "gain": -2.4, "color": -8234772}, {"type": 3, "channels": 0, "frequency": 14000, "q": 5.0, "gain": -5.6, "color": -12636714}, {"type": 3, "channels": 0, "frequency": 19000, "q": 4.6, "gain": -4.4, "color": -12729309}]}]