[{"name": "EQ to See Audio x Crinacle Yume Midnight (AVG)", "preamp": 0.0, "parametric": true, "bands": [{"type": 0, "channels": 0, "frequency": 90, "q": 0, "gain": 0.0, "color": 0}, {"type": 1, "channels": 0, "frequency": 10000, "q": 0, "gain": 0.0, "color": 0}, {"type": 3, "channels": 0, "frequency": 20, "q": 1.1, "gain": 1.9, "color": -2659792}, {"type": 3, "channels": 0, "frequency": 76, "q": 4.0, "gain": 1.2, "color": -8366518}, {"type": 3, "channels": 0, "frequency": 100, "q": 4.7, "gain": -1.2, "color": -7715155}, {"type": 3, "channels": 0, "frequency": 130, "q": 1.5, "gain": -2.4, "color": -5365348}, {"type": 3, "channels": 0, "frequency": 170, "q": 5.0, "gain": -0.4, "color": -1177810}, {"type": 3, "channels": 0, "frequency": 500, "q": 1.6, "gain": 1.2, "color": -9618504}, {"type": 3, "channels": 0, "frequency": 2000, "q": 1.7, "gain": -1.6, "color": -13223069}, {"type": 3, "channels": 0, "frequency": 3800, "q": 5.0, "gain": -0.9, "color": -16522806}, {"type": 3, "channels": 0, "frequency": 5000, "q": 5.0, "gain": -2.4, "color": -671817}, {"type": 3, "channels": 0, "frequency": 6400, "q": 3.1, "gain": 4.7, "color": -10559465}, {"type": 3, "channels": 0, "frequency": 7900, "q": 5.0, "gain": -2.9, "color": -15201667}, {"type": 3, "channels": 0, "frequency": 10000, "q": 3.0, "gain": 10.2, "color": -4266508}, {"type": 3, "channels": 0, "frequency": 12000, "q": 4.6, "gain": -9.6, "color": -4891994}, {"type": 3, "channels": 0, "frequency": 13000, "q": 2.1, "gain": -5.4, "color": -4969769}]}]