[{"name": "EQ to Sennheiser IE300 (AVG)", "preamp": 0.0, "parametric": true, "bands": [{"type": 0, "channels": 0, "frequency": 90, "q": 0, "gain": 0.0, "color": 0}, {"type": 1, "channels": 0, "frequency": 10000, "q": 0, "gain": 0.0, "color": 0}, {"type": 3, "channels": 0, "frequency": 21, "q": 2.8, "gain": 2.0, "color": -9072925}, {"type": 3, "channels": 0, "frequency": 24, "q": 0.3, "gain": 11.9, "color": -13002998}, {"type": 3, "channels": 0, "frequency": 170, "q": 2.6, "gain": -0.8, "color": -6461091}, {"type": 3, "channels": 0, "frequency": 380, "q": 3.4, "gain": -1.7, "color": -2843776}, {"type": 3, "channels": 0, "frequency": 1000, "q": 1.2, "gain": -1.2, "color": -7190379}, {"type": 3, "channels": 0, "frequency": 1900, "q": 2.9, "gain": 1.2, "color": -13998279}, {"type": 3, "channels": 0, "frequency": 3100, "q": 2.1, "gain": -6.0, "color": -14370083}, {"type": 3, "channels": 0, "frequency": 5200, "q": 5.0, "gain": 2.9, "color": -6139836}, {"type": 3, "channels": 0, "frequency": 6000, "q": 4.9, "gain": -4.9, "color": -8015720}, {"type": 3, "channels": 0, "frequency": 6900, "q": 5.0, "gain": 6.3, "color": -8167273}, {"type": 3, "channels": 0, "frequency": 8100, "q": 5.0, "gain": -3.9, "color": -14901226}, {"type": 3, "channels": 0, "frequency": 10000, "q": 1.7, "gain": 11.5, "color": -7628938}, {"type": 3, "channels": 0, "frequency": 11000, "q": 4.3, "gain": -3.2, "color": -8534991}, {"type": 3, "channels": 0, "frequency": 15000, "q": 2.1, "gain": 8.4, "color": -7767322}]}]