[{"name": "EQ to Audeze LCD-5 (AVG)", "preamp": 0.0, "parametric": true, "bands": [{"type": 0, "channels": 0, "frequency": 90, "q": 0, "gain": 0.0, "color": 0}, {"type": 1, "channels": 0, "frequency": 10000, "q": 0, "gain": 0.0, "color": 0}, {"type": 3, "channels": 0, "frequency": 25, "q": 0.2, "gain": -6.0, "color": -6658848}, {"type": 3, "channels": 0, "frequency": 62, "q": 3.4, "gain": 0.7, "color": -11916257}, {"type": 3, "channels": 0, "frequency": 210, "q": 2.1, "gain": -1.8, "color": -7370133}, {"type": 3, "channels": 0, "frequency": 450, "q": 4.7, "gain": 1.1, "color": -8782199}, {"type": 3, "channels": 0, "frequency": 1200, "q": 0.9, "gain": 1.6, "color": -12113060}, {"type": 3, "channels": 0, "frequency": 2500, "q": 2.4, "gain": -2.9, "color": -15459117}, {"type": 3, "channels": 0, "frequency": 3500, "q": 3.1, "gain": 3.9, "color": -14538358}, {"type": 3, "channels": 0, "frequency": 4800, "q": 5.0, "gain": -1.9, "color": -2204264}, {"type": 3, "channels": 0, "frequency": 5500, "q": 5.0, "gain": 2.0, "color": -14747482}, {"type": 3, "channels": 0, "frequency": 5700, "q": 1.8, "gain": -4.5, "color": -4414191}, {"type": 3, "channels": 0, "frequency": 7400, "q": 4.8, "gain": -1.9, "color": -5635721}, {"type": 3, "channels": 0, "frequency": 8600, "q": 5.0, "gain": 3.0, "color": -3946096}, {"type": 3, "channels": 0, "frequency": 10000, "q": 2.0, "gain": 2.4, "color": -7364105}, {"type": 3, "channels": 0, "frequency": 13000, "q": 3.2, "gain": -9.3, "color": -13297200}]}]