[{"name": "EQ to Moondrop Stellaris (AVG)", "preamp": 0.0, "parametric": true, "bands": [{"type": 0, "channels": 0, "frequency": 90, "q": 0, "gain": 0.0, "color": 0}, {"type": 1, "channels": 0, "frequency": 10000, "q": 0, "gain": 0.0, "color": 0}, {"type": 3, "channels": 0, "frequency": 34, "q": 0.3, "gain": -2.8, "color": -14712554}, {"type": 3, "channels": 0, "frequency": 90, "q": 3.0, "gain": -1.4, "color": -9881478}, {"type": 3, "channels": 0, "frequency": 140, "q": 2.9, "gain": 3.1, "color": -15371932}, {"type": 3, "channels": 0, "frequency": 190, "q": 5.0, "gain": -0.8, "color": -8725809}, {"type": 3, "channels": 0, "frequency": 260, "q": 4.0, "gain": 0.7, "color": -7707870}, {"type": 3, "channels": 0, "frequency": 500, "q": 1.1, "gain": -2.1, "color": -907578}, {"type": 3, "channels": 0, "frequency": 2100, "q": 2.1, "gain": 5.8, "color": -12313019}, {"type": 3, "channels": 0, "frequency": 3600, "q": 2.0, "gain": -6.2, "color": -10470657}, {"type": 3, "channels": 0, "frequency": 4300, "q": 5.0, "gain": -2.4, "color": -8290282}, {"type": 3, "channels": 0, "frequency": 5100, "q": 5.0, "gain": 3.2, "color": -1946584}, {"type": 3, "channels": 0, "frequency": 8700, "q": 5.0, "gain": -2.4, "color": -5566123}, {"type": 3, "channels": 0, "frequency": 11000, "q": 3.2, "gain": -5.1, "color": -3845922}, {"type": 3, "channels": 0, "frequency": 14000, "q": 5.0, "gain": 3.8, "color": -13535581}, {"type": 3, "channels": 0, "frequency": 17000, "q": 0.4, "gain": 8.7, "color": -10994723}]}]