[{"name": "EQ to Simgot EM6L (AVG)", "preamp": 0.0, "parametric": true, "bands": [{"type": 0, "channels": 0, "frequency": 90, "q": 0, "gain": 0.0, "color": 0}, {"type": 1, "channels": 0, "frequency": 10000, "q": 0, "gain": 0.0, "color": 0}, {"type": 3, "channels": 0, "frequency": 21, "q": 1.5, "gain": 6.5, "color": -6413571}, {"type": 3, "channels": 0, "frequency": 36, "q": 5.0, "gain": 2.0, "color": -12640105}, {"type": 3, "channels": 0, "frequency": 50, "q": 1.0, "gain": -1.1, "color": -9243359}, {"type": 3, "channels": 0, "frequency": 140, "q": 3.7, "gain": -2.0, "color": -15810146}, {"type": 3, "channels": 0, "frequency": 180, "q": 4.0, "gain": 1.9, "color": -16580794}, {"type": 3, "channels": 0, "frequency": 390, "q": 2.5, "gain": -1.9, "color": -4124335}, {"type": 3, "channels": 0, "frequency": 600, "q": 0.6, "gain": -2.1, "color": -4688381}, {"type": 3, "channels": 0, "frequency": 640, "q": 2.2, "gain": 0.4, "color": -1331263}, {"type": 3, "channels": 0, "frequency": 970, "q": 3.0, "gain": -2.0, "color": -16056129}, {"type": 3, "channels": 0, "frequency": 1400, "q": 3.8, "gain": 0.9, "color": -2289384}, {"type": 3, "channels": 0, "frequency": 1700, "q": 1.2, "gain": 3.8, "color": -4292290}, {"type": 3, "channels": 0, "frequency": 4400, "q": 3.3, "gain": 5.3, "color": -5605472}, {"type": 3, "channels": 0, "frequency": 9100, "q": 2.3, "gain": -8.0, "color": -11644207}, {"type": 3, "channels": 0, "frequency": 15000, "q": 0.7, "gain": 4.3, "color": -1566002}]}]