[{"name": "EQ to Simgot EA1000 (White Filter) (AVG)", "preamp": 0.0, "parametric": true, "bands": [{"type": 0, "channels": 0, "frequency": 90, "q": 0, "gain": 0.0, "color": 0}, {"type": 1, "channels": 0, "frequency": 10000, "q": 0, "gain": 0.0, "color": 0}, {"type": 3, "channels": 0, "frequency": 26, "q": 0.3, "gain": 6.3, "color": -14623954}, {"type": 3, "channels": 0, "frequency": 92, "q": 1.9, "gain": -0.8, "color": -3056436}, {"type": 3, "channels": 0, "frequency": 130, "q": 2.6, "gain": 1.5, "color": -9260587}, {"type": 3, "channels": 0, "frequency": 210, "q": 3.7, "gain": 0.7, "color": -4328409}, {"type": 3, "channels": 0, "frequency": 380, "q": 3.6, "gain": -0.9, "color": -15887524}, {"type": 3, "channels": 0, "frequency": 530, "q": 0.6, "gain": -2.8, "color": -11737185}, {"type": 3, "channels": 0, "frequency": 1800, "q": 5.0, "gain": -0.6, "color": -3071420}, {"type": 3, "channels": 0, "frequency": 2100, "q": 2.1, "gain": 7.2, "color": -9933932}, {"type": 3, "channels": 0, "frequency": 3300, "q": 2.5, "gain": -5.5, "color": -10021876}, {"type": 3, "channels": 0, "frequency": 4900, "q": 2.7, "gain": 6.0, "color": -16148947}, {"type": 3, "channels": 0, "frequency": 7000, "q": 3.2, "gain": 3.0, "color": -10177193}, {"type": 3, "channels": 0, "frequency": 9500, "q": 2.0, "gain": -4.2, "color": -13140628}, {"type": 3, "channels": 0, "frequency": 12000, "q": 5.0, "gain": 9.2, "color": -10929907}, {"type": 3, "channels": 0, "frequency": 15000, "q": 5.0, "gain": 0.7, "color": -8950500}]}]