[{"name": "EQ to Simgot EM6L (AVG)", "preamp": 0.0, "parametric": true, "bands": [{"type": 0, "channels": 0, "frequency": 90, "q": 0, "gain": 0.0, "color": 0}, {"type": 1, "channels": 0, "frequency": 10000, "q": 0, "gain": 0.0, "color": 0}, {"type": 3, "channels": 0, "frequency": 30, "q": 0.5, "gain": 1.1, "color": -9883808}, {"type": 3, "channels": 0, "frequency": 100, "q": 2.6, "gain": 1.4, "color": -5786512}, {"type": 3, "channels": 0, "frequency": 130, "q": 4.5, "gain": -3.2, "color": -8616898}, {"type": 3, "channels": 0, "frequency": 180, "q": 4.9, "gain": 1.4, "color": -14409354}, {"type": 3, "channels": 0, "frequency": 250, "q": 0.3, "gain": 0.6, "color": -6161913}, {"type": 3, "channels": 0, "frequency": 510, "q": 5.0, "gain": 0.7, "color": -14213138}, {"type": 3, "channels": 0, "frequency": 1900, "q": 1.0, "gain": -2.4, "color": -9031184}, {"type": 3, "channels": 0, "frequency": 3400, "q": 2.1, "gain": 2.4, "color": -9358330}, {"type": 3, "channels": 0, "frequency": 4900, "q": 5.0, "gain": -1.6, "color": -14942107}, {"type": 3, "channels": 0, "frequency": 6500, "q": 3.8, "gain": 2.7, "color": -2066017}, {"type": 3, "channels": 0, "frequency": 7800, "q": 5.0, "gain": -2.0, "color": -14584627}, {"type": 3, "channels": 0, "frequency": 9400, "q": 4.2, "gain": 7.8, "color": -2094122}, {"type": 3, "channels": 0, "frequency": 11000, "q": 4.6, "gain": -2.3, "color": -10915217}, {"type": 3, "channels": 0, "frequency": 14000, "q": 5.0, "gain": 6.8, "color": -5880777}]}]