[{"name": "EQ to Moondrop Stellaris (AVG)", "preamp": 0.0, "parametric": true, "bands": [{"type": 0, "channels": 0, "frequency": 90, "q": 0, "gain": 0.0, "color": 0}, {"type": 1, "channels": 0, "frequency": 10000, "q": 0, "gain": 0.0, "color": 0}, {"type": 3, "channels": 0, "frequency": 64, "q": 0.5, "gain": -1.6, "color": -10787710}, {"type": 3, "channels": 0, "frequency": 99, "q": 2.5, "gain": -0.8, "color": -15687230}, {"type": 3, "channels": 0, "frequency": 120, "q": 4.8, "gain": 1.5, "color": -8052391}, {"type": 3, "channels": 0, "frequency": 160, "q": 1.8, "gain": 3.1, "color": -2332964}, {"type": 3, "channels": 0, "frequency": 410, "q": 4.6, "gain": 0.5, "color": -1016946}, {"type": 3, "channels": 0, "frequency": 570, "q": 0.7, "gain": -1.8, "color": -14233121}, {"type": 3, "channels": 0, "frequency": 2100, "q": 2.1, "gain": 4.8, "color": -16121807}, {"type": 3, "channels": 0, "frequency": 2900, "q": 4.8, "gain": -0.7, "color": -13951580}, {"type": 3, "channels": 0, "frequency": 3500, "q": 2.0, "gain": -4.8, "color": -15690793}, {"type": 3, "channels": 0, "frequency": 4300, "q": 4.7, "gain": -2.0, "color": -16491347}, {"type": 3, "channels": 0, "frequency": 5100, "q": 5.0, "gain": 3.6, "color": -6753902}, {"type": 3, "channels": 0, "frequency": 8700, "q": 5.0, "gain": -6.2, "color": -615890}, {"type": 3, "channels": 0, "frequency": 15000, "q": 0.8, "gain": 11.6, "color": -13479165}]}]