[{"name": "EQ to Simgot EA1000 (White Filter) (AVG)", "preamp": 0.0, "parametric": true, "bands": [{"type": 0, "channels": 0, "frequency": 90, "q": 0, "gain": 0.0, "color": 0}, {"type": 1, "channels": 0, "frequency": 10000, "q": 0, "gain": 0.0, "color": 0}, {"type": 3, "channels": 0, "frequency": 24, "q": 0.2, "gain": -2.2, "color": -11447550}, {"type": 3, "channels": 0, "frequency": 93, "q": 4.6, "gain": -1.7, "color": -16050446}, {"type": 3, "channels": 0, "frequency": 290, "q": 1.8, "gain": 0.5, "color": -14232702}, {"type": 3, "channels": 0, "frequency": 670, "q": 2.0, "gain": -0.8, "color": -16382534}, {"type": 3, "channels": 0, "frequency": 1000, "q": 1.7, "gain": -1.0, "color": -16120559}, {"type": 3, "channels": 0, "frequency": 2100, "q": 2.1, "gain": 4.6, "color": -14988869}, {"type": 3, "channels": 0, "frequency": 2700, "q": 3.3, "gain": 4.3, "color": -2137860}, {"type": 3, "channels": 0, "frequency": 3700, "q": 4.6, "gain": -4.1, "color": -12001160}, {"type": 3, "channels": 0, "frequency": 4700, "q": 3.8, "gain": 2.4, "color": -12025486}, {"type": 3, "channels": 0, "frequency": 5100, "q": 5.0, "gain": 2.8, "color": -1713247}, {"type": 3, "channels": 0, "frequency": 6200, "q": 4.0, "gain": -7.4, "color": -14795954}, {"type": 3, "channels": 0, "frequency": 12000, "q": 1.5, "gain": -8.2, "color": -10613260}, {"type": 3, "channels": 0, "frequency": 15000, "q": 5.0, "gain": 8.2, "color": -2122407}]}]