[{"name": "EQ to Moondrop AriaSnow (AVG)", "preamp": 0.0, "parametric": true, "bands": [{"type": 0, "channels": 0, "frequency": 90, "q": 0, "gain": 0.0, "color": 0}, {"type": 1, "channels": 0, "frequency": 10000, "q": 0, "gain": 0.0, "color": 0}, {"type": 3, "channels": 0, "frequency": 20, "q": 1.6, "gain": -1.1, "color": -6709788}, {"type": 3, "channels": 0, "frequency": 86, "q": 0.6, "gain": 1.5, "color": -13853648}, {"type": 3, "channels": 0, "frequency": 96, "q": 4.3, "gain": -1.5, "color": -7762175}, {"type": 3, "channels": 0, "frequency": 110, "q": 3.4, "gain": 2.1, "color": -16233977}, {"type": 3, "channels": 0, "frequency": 690, "q": 1.2, "gain": -0.9, "color": -1946041}, {"type": 3, "channels": 0, "frequency": 1700, "q": 1.9, "gain": 0.6, "color": -3053046}, {"type": 3, "channels": 0, "frequency": 2300, "q": 4.0, "gain": 0.4, "color": -416491}, {"type": 3, "channels": 0, "frequency": 4600, "q": 4.3, "gain": 1.8, "color": -13351784}, {"type": 3, "channels": 0, "frequency": 8600, "q": 3.1, "gain": 1.6, "color": -4270811}, {"type": 3, "channels": 0, "frequency": 11000, "q": 3.2, "gain": -6.9, "color": -13731159}, {"type": 3, "channels": 0, "frequency": 14000, "q": 3.8, "gain": -1.6, "color": -14797998}, {"type": 3, "channels": 0, "frequency": 15000, "q": 4.7, "gain": 5.8, "color": -5625610}, {"type": 3, "channels": 0, "frequency": 16000, "q": 2.1, "gain": -2.1, "color": -11129014}, {"type": 3, "channels": 0, "frequency": 19000, "q": 2.3, "gain": 4.9, "color": -13524462}]}]