[{"name": "EQ to Focal Utopia (AVG)", "preamp": 0.0, "parametric": true, "bands": [{"type": 0, "channels": 0, "frequency": 90, "q": 0, "gain": 0.0, "color": 0}, {"type": 1, "channels": 0, "frequency": 10000, "q": 0, "gain": 0.0, "color": 0}, {"type": 3, "channels": 0, "frequency": 21, "q": 0.7, "gain": -8.0, "color": -7530951}, {"type": 3, "channels": 0, "frequency": 29, "q": 4.5, "gain": 0.7, "color": -3117987}, {"type": 3, "channels": 0, "frequency": 91, "q": 3.3, "gain": 2.3, "color": -13857672}, {"type": 3, "channels": 0, "frequency": 330, "q": 0.9, "gain": 2.8, "color": -9729433}, {"type": 3, "channels": 0, "frequency": 510, "q": 1.4, "gain": -0.4, "color": -3159574}, {"type": 3, "channels": 0, "frequency": 1200, "q": 1.8, "gain": 1.4, "color": -7531595}, {"type": 3, "channels": 0, "frequency": 2000, "q": 3.0, "gain": -3.4, "color": -13493046}, {"type": 3, "channels": 0, "frequency": 2900, "q": 2.4, "gain": 2.1, "color": -14538764}, {"type": 3, "channels": 0, "frequency": 5000, "q": 5.0, "gain": -2.6, "color": -2898402}, {"type": 3, "channels": 0, "frequency": 7000, "q": 5.0, "gain": -6.2, "color": -12147280}, {"type": 3, "channels": 0, "frequency": 8200, "q": 5.0, "gain": 4.8, "color": -6452633}, {"type": 3, "channels": 0, "frequency": 10000, "q": 1.9, "gain": 9.4, "color": -14565866}, {"type": 3, "channels": 0, "frequency": 12000, "q": 4.5, "gain": -8.2, "color": -2690043}, {"type": 3, "channels": 0, "frequency": 13000, "q": 0.2, "gain": -3.5, "color": -13695367}]}]