[{"name": "EQ to Symphonium Helios (Azla Sedna Tips) (AVG)", "preamp": 0.0, "parametric": true, "bands": [{"type": 0, "channels": 0, "frequency": 90, "q": 0, "gain": 0.0, "color": 0}, {"type": 1, "channels": 0, "frequency": 10000, "q": 0, "gain": 0.0, "color": 0}, {"type": 3, "channels": 0, "frequency": 30, "q": 0.9, "gain": 2.8, "color": -14486693}, {"type": 3, "channels": 0, "frequency": 94, "q": 1.2, "gain": -1.5, "color": -13240402}, {"type": 3, "channels": 0, "frequency": 100, "q": 5.0, "gain": -0.9, "color": -4315371}, {"type": 3, "channels": 0, "frequency": 130, "q": 5.0, "gain": 2.5, "color": -10180392}, {"type": 3, "channels": 0, "frequency": 200, "q": 1.3, "gain": -2.1, "color": -2554172}, {"type": 3, "channels": 0, "frequency": 600, "q": 1.2, "gain": 1.2, "color": -3242605}, {"type": 3, "channels": 0, "frequency": 2200, "q": 2.5, "gain": 1.1, "color": -6034604}, {"type": 3, "channels": 0, "frequency": 3000, "q": 4.7, "gain": -1.1, "color": -14141776}, {"type": 3, "channels": 0, "frequency": 3600, "q": 2.5, "gain": -3.4, "color": -3294344}, {"type": 3, "channels": 0, "frequency": 4900, "q": 5.0, "gain": -1.9, "color": -14295358}, {"type": 3, "channels": 0, "frequency": 6000, "q": 3.1, "gain": 4.9, "color": -12762413}, {"type": 3, "channels": 0, "frequency": 9500, "q": 4.6, "gain": 2.2, "color": -10922160}, {"type": 3, "channels": 0, "frequency": 10000, "q": 2.7, "gain": -2.4, "color": -6628659}, {"type": 3, "channels": 0, "frequency": 11000, "q": 5.0, "gain": -5.3, "color": -2949885}]}]