[{"name": "EQ to Moondrop Quarks (AVG)", "preamp": 0.0, "parametric": true, "bands": [{"type": 0, "channels": 0, "frequency": 90, "q": 0, "gain": 0.0, "color": 0}, {"type": 1, "channels": 0, "frequency": 10000, "q": 0, "gain": 0.0, "color": 0}, {"type": 3, "channels": 0, "frequency": 25, "q": 0.4, "gain": -3.7, "color": -15544849}, {"type": 3, "channels": 0, "frequency": 94, "q": 4.6, "gain": 1.7, "color": -14190808}, {"type": 3, "channels": 0, "frequency": 120, "q": 4.2, "gain": -0.7, "color": -10907869}, {"type": 3, "channels": 0, "frequency": 240, "q": 2.7, "gain": -1.9, "color": -11854531}, {"type": 3, "channels": 0, "frequency": 320, "q": 3.2, "gain": 3.1, "color": -14954425}, {"type": 3, "channels": 0, "frequency": 580, "q": 4.5, "gain": 0.7, "color": -15269309}, {"type": 3, "channels": 0, "frequency": 1700, "q": 0.6, "gain": -2.4, "color": -6356420}, {"type": 3, "channels": 0, "frequency": 2800, "q": 2.9, "gain": 5.6, "color": -10324410}, {"type": 3, "channels": 0, "frequency": 3100, "q": 5.0, "gain": 1.5, "color": -6441961}, {"type": 3, "channels": 0, "frequency": 4200, "q": 4.6, "gain": -2.1, "color": -67553}, {"type": 3, "channels": 0, "frequency": 6000, "q": 4.2, "gain": 3.9, "color": -2186410}, {"type": 3, "channels": 0, "frequency": 9200, "q": 3.5, "gain": 5.8, "color": -13262141}, {"type": 3, "channels": 0, "frequency": 14000, "q": 0.8, "gain": -4.6, "color": -4052457}]}]