[{"name": "EQ to Thieaudio Monarch MkII (AVG)", "preamp": 0.0, "parametric": true, "bands": [{"type": 0, "channels": 0, "frequency": 90, "q": 0, "gain": 0.0, "color": 0}, {"type": 1, "channels": 0, "frequency": 10000, "q": 0, "gain": 0.0, "color": 0}, {"type": 3, "channels": 0, "frequency": 24, "q": 0.3, "gain": 6.1, "color": -7318018}, {"type": 3, "channels": 0, "frequency": 240, "q": 2.5, "gain": -0.9, "color": -4430865}, {"type": 3, "channels": 0, "frequency": 360, "q": 4.5, "gain": -0.5, "color": -6790908}, {"type": 3, "channels": 0, "frequency": 590, "q": 2.3, "gain": -0.5, "color": -9324429}, {"type": 3, "channels": 0, "frequency": 1300, "q": 3.2, "gain": -0.4, "color": -11113868}, {"type": 3, "channels": 0, "frequency": 1800, "q": 1.6, "gain": -0.8, "color": -11640382}, {"type": 3, "channels": 0, "frequency": 3400, "q": 1.6, "gain": 2.7, "color": -15087792}, {"type": 3, "channels": 0, "frequency": 4400, "q": 5.0, "gain": -4.9, "color": -6475440}, {"type": 3, "channels": 0, "frequency": 4400, "q": 1.9, "gain": 2.9, "color": -3874667}, {"type": 3, "channels": 0, "frequency": 5300, "q": 5.0, "gain": 6.2, "color": -12334647}, {"type": 3, "channels": 0, "frequency": 7600, "q": 2.0, "gain": -5.4, "color": -9050607}, {"type": 3, "channels": 0, "frequency": 12000, "q": 3.8, "gain": -1.9, "color": -10293075}, {"type": 3, "channels": 0, "frequency": 15000, "q": 5.0, "gain": 3.7, "color": -560205}, {"type": 3, "channels": 0, "frequency": 18000, "q": 4.6, "gain": 4.9, "color": -14637534}]}]