[{"name": "EQ to Truthear ZeroRED (AVG)", "preamp": 0.0, "parametric": true, "bands": [{"type": 0, "channels": 0, "frequency": 90, "q": 0, "gain": 0.0, "color": 0}, {"type": 1, "channels": 0, "frequency": 10000, "q": 0, "gain": 0.0, "color": 0}, {"type": 3, "channels": 0, "frequency": 23, "q": 3.9, "gain": -0.5, "color": -8257173}, {"type": 3, "channels": 0, "frequency": 31, "q": 2.6, "gain": -0.5, "color": -12141931}, {"type": 3, "channels": 0, "frequency": 68, "q": 1.9, "gain": 2.7, "color": -11221209}, {"type": 3, "channels": 0, "frequency": 160, "q": 1.5, "gain": -2.5, "color": -9075240}, {"type": 3, "channels": 0, "frequency": 190, "q": 4.9, "gain": -0.6, "color": -2416574}, {"type": 3, "channels": 0, "frequency": 420, "q": 4.0, "gain": -0.9, "color": -1910400}, {"type": 3, "channels": 0, "frequency": 640, "q": 1.2, "gain": -1.7, "color": -11292041}, {"type": 3, "channels": 0, "frequency": 1800, "q": 0.8, "gain": 2.1, "color": -14526139}, {"type": 3, "channels": 0, "frequency": 4400, "q": 4.4, "gain": 1.5, "color": -9895695}, {"type": 3, "channels": 0, "frequency": 7200, "q": 5.0, "gain": -2.9, "color": -1903970}, {"type": 3, "channels": 0, "frequency": 9800, "q": 4.5, "gain": -6.0, "color": -2313433}, {"type": 3, "channels": 0, "frequency": 16000, "q": 5.0, "gain": 9.7, "color": -4238978}, {"type": 3, "channels": 0, "frequency": 19000, "q": 1.4, "gain": -9.9, "color": -1171838}]}]