[{"name": "EQ to Audeze LCD-5 (AVG)", "preamp": 0.0, "parametric": true, "bands": [{"type": 0, "channels": 0, "frequency": 90, "q": 0, "gain": 0.0, "color": 0}, {"type": 1, "channels": 0, "frequency": 10000, "q": 0, "gain": 0.0, "color": 0}, {"type": 3, "channels": 0, "frequency": 29, "q": 0.4, "gain": -6.5, "color": -12229333}, {"type": 3, "channels": 0, "frequency": 92, "q": 4.1, "gain": 1.0, "color": -5930262}, {"type": 3, "channels": 0, "frequency": 140, "q": 1.7, "gain": -1.5, "color": -9523334}, {"type": 3, "channels": 0, "frequency": 370, "q": 3.3, "gain": 1.2, "color": -13789535}, {"type": 3, "channels": 0, "frequency": 480, "q": 0.7, "gain": 2.1, "color": -6524966}, {"type": 3, "channels": 0, "frequency": 890, "q": 3.0, "gain": 0.6, "color": -2220499}, {"type": 3, "channels": 0, "frequency": 2100, "q": 2.5, "gain": -3.1, "color": -3786205}, {"type": 3, "channels": 0, "frequency": 3300, "q": 2.6, "gain": 3.8, "color": -5197542}, {"type": 3, "channels": 0, "frequency": 4900, "q": 1.5, "gain": -5.7, "color": -2226953}, {"type": 3, "channels": 0, "frequency": 7200, "q": 4.6, "gain": -4.0, "color": -2617912}, {"type": 3, "channels": 0, "frequency": 9000, "q": 3.4, "gain": 6.1, "color": -13451193}]}]