[{"name": "EQ to Kiwi Ears x Crinacle Singolo (R)", "preamp": 0.0, "parametric": true, "bands": [{"type": 0, "channels": 0, "frequency": 90, "q": 0, "gain": 0.0, "color": 0}, {"type": 1, "channels": 0, "frequency": 10000, "q": 0, "gain": 0.0, "color": 0}, {"type": 3, "channels": 0, "frequency": 22, "q": 0.4, "gain": 6.3, "color": -9337711}, {"type": 3, "channels": 0, "frequency": 110, "q": 2.0, "gain": 0.9, "color": -490735}, {"type": 3, "channels": 0, "frequency": 150, "q": 4.7, "gain": -2.5, "color": -1929765}, {"type": 3, "channels": 0, "frequency": 260, "q": 3.9, "gain": -0.7, "color": -720499}, {"type": 3, "channels": 0, "frequency": 390, "q": 3.8, "gain": 1.6, "color": -11737980}, {"type": 3, "channels": 0, "frequency": 1800, "q": 1.5, "gain": -0.8, "color": -637634}, {"type": 3, "channels": 0, "frequency": 4300, "q": 2.1, "gain": 1.2, "color": -13813630}, {"type": 3, "channels": 0, "frequency": 6800, "q": 2.9, "gain": -1.8, "color": -731082}, {"type": 3, "channels": 0, "frequency": 9200, "q": 4.5, "gain": 2.7, "color": -16710230}, {"type": 3, "channels": 0, "frequency": 19000, "q": 0.8, "gain": -7.8, "color": -11934468}]}]