[{"name": "EQ to Simgot EA500LM (Red Filter) (AVG)", "preamp": 0.0, "parametric": true, "bands": [{"type": 0, "channels": 0, "frequency": 90, "q": 0, "gain": 0.0, "color": 0}, {"type": 1, "channels": 0, "frequency": 10000, "q": 0, "gain": 0.0, "color": 0}, {"type": 3, "channels": 0, "frequency": 20, "q": 1.1, "gain": 2.1, "color": -7312081}, {"type": 3, "channels": 0, "frequency": 80, "q": 1.6, "gain": -1.2, "color": -2583083}, {"type": 3, "channels": 0, "frequency": 98, "q": 5.0, "gain": -1.0, "color": -16689361}, {"type": 3, "channels": 0, "frequency": 130, "q": 3.0, "gain": 2.0, "color": -14199772}, {"type": 3, "channels": 0, "frequency": 180, "q": 4.0, "gain": -1.0, "color": -13305848}, {"type": 3, "channels": 0, "frequency": 460, "q": 0.7, "gain": -2.9, "color": -1738109}, {"type": 3, "channels": 0, "frequency": 1500, "q": 3.2, "gain": 0.5, "color": -4407834}, {"type": 3, "channels": 0, "frequency": 2100, "q": 3.7, "gain": -1.0, "color": -2466546}, {"type": 3, "channels": 0, "frequency": 3200, "q": 2.3, "gain": 1.6, "color": -7597876}, {"type": 3, "channels": 0, "frequency": 4700, "q": 4.9, "gain": -1.9, "color": -10747403}, {"type": 3, "channels": 0, "frequency": 6500, "q": 1.1, "gain": 5.7, "color": -1929313}, {"type": 3, "channels": 0, "frequency": 9500, "q": 3.8, "gain": -6.4, "color": -10097092}, {"type": 3, "channels": 0, "frequency": 12000, "q": 2.7, "gain": 11.4, "color": -4361804}, {"type": 3, "channels": 0, "frequency": 16000, "q": 1.7, "gain": -9.6, "color": -4776299}]}]